.gitignore
MANIFEST.in
README.rst
bootstrap.py
buildout.cfg
setup.py
collective/__init__.py
collective.gallery.egg-info/PKG-INFO
collective.gallery.egg-info/SOURCES.txt
collective.gallery.egg-info/dependency_links.txt
collective.gallery.egg-info/entry_points.txt
collective.gallery.egg-info/namespace_packages.txt
collective.gallery.egg-info/not-zip-safe
collective.gallery.egg-info/requires.txt
collective.gallery.egg-info/top_level.txt
collective/gallery/__init__.py
collective/gallery/brain.py
collective/gallery/cache.py
collective/gallery/configure.zcml
collective/gallery/core.py
collective/gallery/folder.py
collective/gallery/i18n.py
collective/gallery/interfaces.py
collective/gallery/rebuild_i18n.sh
collective/gallery/topic.py
collective/gallery/upgrades.py
collective/gallery/vocabularies.py
collective/gallery/.tx/config
collective/gallery/browser/__init__.py
collective/gallery/browser/galleries_view.pt
collective/gallery/browser/galleries_view.py
collective/gallery/browser/templates/flickr_slideshow.pt
collective/gallery/browser/templates/picasa_slideshow.pt
collective/gallery/browser/templates/placegallery.pt
collective/gallery/link/__init__.py
collective/gallery/link/base.py
collective/gallery/link/facebook.py
collective/gallery/link/flickr.py
collective/gallery/link/picasaweb.py
collective/gallery/locales/collective.gallery.pot
collective/gallery/locales/de/LC_MESSAGES/collective.gallery.po
collective/gallery/locales/en/LC_MESSAGES/collective.gallery.po
collective/gallery/locales/es/LC_MESSAGES/collective.gallery.po
collective/gallery/locales/fr/LC_MESSAGES/collective.gallery.po
collective/gallery/locales/it/LC_MESSAGES/collective.gallery.po
collective/gallery/profiles/default/browserlayer.xml
collective/gallery/profiles/default/metadata.xml
collective/gallery/profiles/default/registry.xml
collective/gallery/profiles/uninstall/componentregistry.xml
collective/gallery/profiles/zclean/componentregistry.xml
collective/gallery/profiles/zclean/cssregistry.xml
collective/gallery/profiles/zclean/jsregistry.xml
collective/gallery/profiles/zclean/metadata.xml
collective/gallery/profiles/zclean/portlets.xml
collective/gallery/profiles/zclean/propertiestool.xml
collective/gallery/profiles/zclean/skins.xml
collective/gallery/profiles/zclean/types/Folder.xml
collective/gallery/profiles/zclean/types/Link.xml
