Metadata-Version: 1.0
Name: collective.gallery
Version: 2.0.1
Summary: Base gallery for plone with external services support
Home-page: https://github.com/collective/collective.gallery
Author: JeanMichel FRANCOIS aka toutpt
Author-email: toutpt@gmail.com
License: GPL
Keywords: plone gallery
Platform: UNKNOWN
Classifier: Framework :: Plone
Classifier: Framework :: Plone :: 4.0
Classifier: Framework :: Plone :: 4.1
Classifier: Framework :: Plone :: 4.2
Classifier: Programming Language :: Python
